Metadata-Version: 2.1
Name: jswitch
Version: 0.0.1
Summary: JSwitch: text-based menu for switching between Java environments
Home-page: https://github.com/DevDungeon/issh
Author: DevDungeon
Author-email: nanodano@devdungeon.com
License: UNKNOWN
Platform: UNKNOWN
Classifier: License :: OSI Approved :: GNU General Public License v3 (GPLv3)
Requires-Python: <3.6
